python_architecture_linter/__init__.py
python_architecture_linter/file_to_module.py
python_architecture_linter/linter.py
python_architecture_linter/node_navigators.py
python_architecture_linter/tree_structure.py
python_architecture_linter/types.py
python_architecture_linter/ast_validators/__init__.py
python_architecture_linter/ast_validators/class_validators.py
python_architecture_linter/ast_validators/function_validators.py
python_architecture_linter/ast_validators/nodeng_validator.py
python_architecture_linter/domain_objects/__init__.py
python_architecture_linter/domain_objects/file.py
python_architecture_linter/domain_objects/validation_result.py
python_architecture_linter/domain_objects/tests/__init__.py
python_architecture_linter-0.1.4.dist-info/METADATA
python_architecture_linter-0.1.4.dist-info/WHEEL
python_architecture_linter-0.1.4.dist-info/namespace_packages.txt
python_architecture_linter-0.1.4.dist-info/top_level.txt
python_architecture_linter-0.1.4.dist-info/RECORD
