Metadata-Version: 2.1
Name: python-architecture-linter
Version: 0.1.4
Summary: Core lib for linter.
Home-page: UNKNOWN
Author: Brian Graham
License: UNKNOWN
Platform: UNKNOWN
Classifier: Programming Language :: Python :: 3.9
Requires-Dist: astroid (<3.0.0,>=2.5.8)
